measpy/__init__.py
measpy/__main__.py
measpy/_plot_tools.py
measpy/_tools.py
measpy/_version.py
measpy/audio.py
measpy/measurement.py
measpy/ni.py
measpy/pico.py
measpy/signal.py
measpy/utils.py
measpy-0.3.dist-info/LICENSE
measpy-0.3.dist-info/METADATA
measpy-0.3.dist-info/WHEEL
measpy-0.3.dist-info/top_level.txt
measpy-0.3.dist-info/RECORD
