Metadata-Version: 2.1
Name: measpy
Version: 0.3
Summary: Measurements with Python
Author: Olivier Doaré
Author-email: <olivier.doare@ensta-paris.fr>
Keywords: Python,Measurements,Data acquisition,Signal processing
Classifier: Development Status :: 3 - Alpha
Classifier: Programming Language :: Python :: 3
License-File: LICENSE
Requires-Dist: numpy
Requires-Dist: matplotlib
Requires-Dist: unyt
Requires-Dist: csaps
Requires-Dist: h5py
